playfulrequests/.DS_Store
playfulrequests/__init__.py
playfulrequests/__version__.py
playfulrequests/bin/LICENSE.txt
playfulrequests/bin/__init__.py
playfulrequests/browser.py
playfulrequests/cffi.py
playfulrequests/client.py
playfulrequests/cookies.py
playfulrequests/exceptions.py
playfulrequests/extensions.py
playfulrequests/headers.py
playfulrequests/parser.py
playfulrequests/playwright_mock/__init__.py
playfulrequests/playwright_mock/context.py
playfulrequests/playwright_mock/element_handle.py
playfulrequests/playwright_mock/faker.py
playfulrequests/playwright_mock/frame.py
playfulrequests/playwright_mock/frame_locator.py
playfulrequests/playwright_mock/js_handle.py
playfulrequests/playwright_mock/locale.json
playfulrequests/playwright_mock/locator.py
playfulrequests/playwright_mock/mouse.py
playfulrequests/playwright_mock/page.py
playfulrequests/playwright_mock/playwright_mock.py
playfulrequests/playwright_mock/proxy_manager.py
playfulrequests/reqs.py
playfulrequests/response.py
playfulrequests/session.py
playfulrequests/toolbelt.py
playfulrequests-0.8.9b0.dist-info/LICENSE
playfulrequests-0.8.9b0.dist-info/METADATA
playfulrequests-0.8.9b0.dist-info/WHEEL
playfulrequests-0.8.9b0.dist-info/RECORD
