Metadata-Version: 2.1
Name: PlayfulRequests
Version: 0.8.9b0
Summary: PlayfulRequests (human requests) is a simple, configurable, feature-rich, replacement for the Python requests library. This is a fork of hrequests.
Home-page: https://github.com/fabiocantone/frequests
License: Apache-2.0
Keywords: tls,client,http,scraping,requests,humans,playwright
Author: fabiocan
Author-email: fabio@cantone.me
Requires-Python: >=3.7,<4.0
Classifier: License :: OSI Approved :: Apache Software License
Classifier: Programming Language :: Python :: 3
Classifier: Programming Language :: Python :: 3.7
Classifier: Programming Language :: Python :: 3.8
Classifier: Programming Language :: Python :: 3.9
Classifier: Programming Language :: Python :: 3.10
Classifier: Programming Language :: Python :: 3.11
Classifier: Programming Language :: Python :: 3.12
Classifier: Topic :: Internet :: WWW/HTTP
Classifier: Topic :: Internet :: WWW/HTTP :: Browsers
Classifier: Topic :: Software Development :: Libraries :: Python Modules
Provides-Extra: all
Requires-Dist: aioprocessing
Requires-Dist: async-class
Requires-Dist: gevent
Requires-Dist: geventhttpclient
Requires-Dist: httpx
Requires-Dist: msvc-runtime ; sys_platform == "win32"
Requires-Dist: numpy
Requires-Dist: orjson
Requires-Dist: parse
Requires-Dist: playwright (==1.34.0) ; extra == "all"
Requires-Dist: playwright-stealth ; extra == "all"
Requires-Dist: pycryptodome ; extra == "all"
Requires-Dist: rich
Requires-Dist: selectolax
Requires-Dist: urllib3
Project-URL: Repository, https://github.com/fabiocantone/frequests
